iqrm/__init__.py
iqrm/_version.py
iqrm/core.py
iqrm-0.2.0.dist-info/licenses/LICENSE
iqrm-0.2.0.dist-info/METADATA
iqrm-0.2.0.dist-info/WHEEL
iqrm-0.2.0.dist-info/top_level.txt
iqrm-0.2.0.dist-info/RECORD
