Metadata-Version: 2.4
Name: iqrm
Version: 0.2.0
Summary: A minimal implementation of the IQRM interference flagging algorithm
Author-email: Vincent Morello <vmorello@gmail.com>
License-Expression: MIT
Project-URL: Documentation, https://github.com/vmorello/iqrm
Project-URL: Homepage, https://github.com/vmorello/iqrm
Project-URL: Issues, https://github.com/vmorello/iqrm/issues
Project-URL: Source, https://github.com/vmorello/iqrm
Classifier: Operating System :: Unix
Classifier: Programming Language :: Python :: 3.8
Classifier: Programming Language :: Python :: 3.9
Classifier: Programming Language :: Python :: 3.10
Classifier: Programming Language :: Python :: 3.11
Classifier: Programming Language :: Python :: 3.12
Classifier: Programming Language :: Python :: 3.13
Classifier: Topic :: Scientific/Engineering :: Astronomy
Requires-Python: >=3.8
License-File: LICENSE
Requires-Dist: numpy
Dynamic: license-file
